dcsm/__init__.py
dcsm/commands/__init__.py
dcsm/commands/create_mount.py
dcsm/commands/create_user.py
dcsm/commands/delete_user.py
dcsm/commands/give_read_access.py
dcsm/commands/give_write_access.py
dcsm/commands/initialize.py
dcsm/commands/main.py
dcsm/commands/mount.py
dcsm/config.py
dcsm/database.py
dcsm/juicefs.py
dcsm/minio.py
dcsm/minio_policies/read_template.json
dcsm/minio_policies/write_template.json
dcsm/utils.py
dcsm-0.0.1.dist-info/METADATA
dcsm-0.0.1.dist-info/WHEEL
dcsm-0.0.1.dist-info/entry_points.txt
dcsm-0.0.1.dist-info/RECORD
